thinking_tests/__init__.py
thinking_tests/adapter.py
thinking_tests/current.py
thinking_tests/decorators.py
thinking_tests/fluent_decorator.py
thinking_tests/outcome.py
thinking_tests/protocol.py
thinking_tests/simple.py
thinking_tests/utils.py
thinking_tests/aspect/__init__.py
thinking_tests/aspect/custom.py
thinking_tests/aspect/defaults.py
thinking_tests/aspect/protocol.py
thinking_tests/aspect/weaving.py
thinking_tests/forks/__init__.py
thinking_tests/forks/junit_xml.py
thinking_tests/forks/template.html
thinking_tests/forks/vjunit.py
thinking_tests/runner/__init__.py
thinking_tests/runner/default_impl.py
thinking_tests/runner/protocol.py
thinking_tests/runner/run.py
thinking_tests/runner/singleton.py
thinking_tests/runner/unittest.py
thinking_tests/running/__init__.py
thinking_tests/running/bootstrap.py
thinking_tests/running/capture_logs.py
thinking_tests/running/start.py
thinking_tests/running/test_config.py
thinking_tests/running/test_setup_action.py
thinking_tests-0.0.4.dist-info/LICENSE
thinking_tests-0.0.4.dist-info/METADATA
thinking_tests-0.0.4.dist-info/WHEEL
thinking_tests-0.0.4.dist-info/top_level.txt
thinking_tests-0.0.4.dist-info/RECORD
