Metadata-Version: 2.1
Name: thinking-tests
Version: 0.0.4
Summary: Declarative API over unittest with customizable auto-discovery, test lifecycle and handy integrations
Author-email: Filip Malczak <filip.malczak@gmail.com>
License: MIT License
Project-URL: Homepage, https://github.com/FilipMalczak/thinking-tests
Keywords: thinking,test,unittest,junit,report,coverage
Classifier: License :: OSI Approved :: MIT License
Classifier: Programming Language :: Python
Classifier: Programming Language :: Python :: 3
Requires-Python: >=3.12
License-File: LICENSE
Requires-Dist: thinking-modules>=0.0.4
Requires-Dist: thinking-runtime>=0.0.3
Requires-Dist: coverage>=7.6.1
Requires-Dist: jinja2>=3.1.4
